{"1": "Amo ini ang ginpakita sang Ginoong Dios Dios sa akon: Nakita ko ang isa ka alat nga may luto nga mga prutas.", "2": "Nagpamangkot ang Ginoo Ginoo sa akon, “Amos, ano ang nakita mo?” Nagsabat ako, “Isa ka alat nga may luto nga mga prutas.” Dayon nagsiling ang Ginoo Ginoo sa akon, “Nag-abot na ang katapusan # 8:2 katapusan: Sa Hebreo, ang pulong nga “luto nga mga prutas” kag “katapusan” daw pareho kon ihambal. # 8:2 katapusan: Sa Hebreo, ang pulong nga “luto nga mga prutas” kag “katapusan” daw pareho kon ihambal. 8:2 katapusan: Sa Hebreo, ang pulong nga “luto nga mga prutas” kag “katapusan” daw pareho kon ihambal. sang akon katawhan nga taga-Israel. Indi ko na sila pagkaluoyan pa.", "3": "Sa sina nga adlaw nga silutan sila nga silutan sila , ang masadya nga masadya nga pagkinanta sa templo # 8:3 templo: ukon, palasyo # 8:3 templo: ukon, palasyo 8:3 templo: ukon, palasyo mangin paghinibi kay madamo nga patay ang magalinapta bisan diin. Kag dayon wala na gid sing may mabatian nga gahod. # 8:3 Kag…gahod: sa literal, Hipos! # 8:3 Kag…gahod: sa literal, Hipos! 8:3 Kag…gahod: sa literal, Hipos! Ako, Ako, ang Ginoong Dios Dios , ang nagasiling sini.”", "4": "kag nagatinguha sa paglaglag sa ila.", "5": "para makabaligya na kamo sang uyas kag makadaya sa inyo nga pagsukob, pagtakos, kag pagkilo.", "6": "bisan ang iya utang ahaw isa ka paris nga sandalyas.", "7": "“Indi ko gid pagkalimtan ang tanan nga kalautan nga ginhimo ninyo.", "8": "nga daw pareho sang pag-awas kag paghubas sang Suba sang Nilo sa Egypt.", "9": "Ako, Ako, ang Ginoong Dios Dios , ang nagasiling sini.", "10": "Pero mas masakit pa gid ang katapusan sang sini nga mga silot.”", "11": "kundi kagutom kag kauhaw kag kauhaw sa pagpamati sang akon mensahi.", "12": "pero indi gid ninyo ini makita bisan diin kamo magkadto.", "13": "magakalalipong sa kauhaw.", "14": "pagalaglagon kamo kag indi na gid kamo makabangon pa.”"}