{"1": "Ipakita sa amon ang imo kaayo # 67:1 Sa Hebreo may sugpon pa nga “sela,” nga indi klaro ang buot silingon. Makita man ini sa bersikulo 4. # 67:1 Sa Hebreo may sugpon pa nga “sela,” nga indi klaro ang buot silingon. Makita man ini sa bersikulo 4. 67:1 Sa Hebreo may sugpon pa nga “sela,” nga indi klaro ang buot silingon. Makita man ini sa bersikulo 4.", "2": "para mahibaluan sang tanan nga nasyon sa kalibutan ang imo pamaagi kag kaluwasan.", "3": "Kabay pa nga dayawon ka sang tanan nga katawhan, O Dios.", "4": "tungod kay matarong ang imo paghukom sa ila kag ginatuytuyan mo sila.", "5": "Kabay pa nga dayawon ka sang tanan nga katawhan, O Dios."}