{"1": "Gani karon, Gani karon, pamatii ang akon mga pangamuyo kag kaluoyi ako.", "2": "kag sa pagsunod sa kabutigan? # 4:2 sa paghigugma…kabutigan: Siguro ang buot silingon amo ang pagsimba sa mga dios-dios. # 4:2 sa paghigugma…kabutigan: Siguro ang buot silingon amo ang pagsimba sa mga dios-dios. 4:2 sa paghigugma…kabutigan: Siguro ang buot silingon amo ang pagsimba sa mga dios-dios. # 4:2 Sa Hebreo may sugpon pa nga “sela,” nga indi klaro ang buot silingon. Makita man ini sa bersikulo 4. # 4:2 Sa Hebreo may sugpon pa nga “sela,” nga indi klaro ang buot silingon. Makita man ini sa bersikulo 4. 4:2 Sa Hebreo may sugpon pa nga “sela,” nga indi klaro ang buot silingon. Makita man ini sa bersikulo 4.", "3": "Amo gani nga Amo gani nga pamatian niya ako kon magpanawag ako sa iya.", "4": "Kag samtang nagahigda kamo, magpakalinong kamo kag magpamalandong.", "5": "kag maghalad sa iya sing husto nga mga halad. # 4:5 maghalad…halad: ukon, maghalad sa iya nga husto ang inyo kabuhi # 4:5 maghalad…halad: ukon, maghalad sa iya nga husto ang inyo kabuhi 4:5 maghalad…halad: ukon, maghalad sa iya nga husto ang inyo kabuhi", "6": "Ipakita ang imo kaayo sa amon!”", "7": "nga bugana ang ila mga uyas kag duga sang ubas.", "8": "tungod kay ginabantayan mo ako, Ginoo Ginoo ."}