{"1": "Ngaa bala nagapanago ka sa tion sang kalisod?", "2": "ang ila ginaplano nga malain sa iban.", "3": "Sila nga mga dalok nagapakamalaot kag nagayaguta sa imo, Ginoo Ginoo . # 10:3 Sila… Ginoo : ukon, Ginapakamaayo nila ang mga dalok, pero ginayaguta ka nila, Ginoo . # 10:3 Sila… Ginoo : ukon, Ginapakamaayo nila ang mga dalok, pero ginayaguta ka nila, Ginoo . 10:3 Sila… Ginoo : Ginoo ukon, Ginapakamaayo nila ang mga dalok, pero ginayaguta ka nila, Ginoo . Ginoo", "4": "Wala gid sila nagahunahuna parte sa imo.", "5": "Ginahikayan pa nila ang tanan nila nga kaaway.", "6": "kag wala sing malain nga matabo sa ila.", "7": "nga makahalit sa iban.", "8": "nga nagabantay sa mga inosente nga magaagi para patyon nila.", "9": "kag kon madakop na gani nila ginaguyod nila dayon.", "10": "hasta nga indi na ini makabangon.", "11": "kag wala gid niya makita ang ila ginahimo.", "12": "Indi pagpabay-i ang mga kubos.", "13": "Nagasiling pa sila nga indi mo kuno sila pagsilutan.", "14": "kag ginabuligan mo sila.", "15": "Siluti sila sa ila mga kalautan hasta nga untatan na nila ini.", "16": "nga imo gintuga gintuga .", "17": "Sabta ang ila pangamuyo kag palig-una sila.", "18": "para indi na sila pagpahugon sang tawo nga halin man lang sa duta."}