{"1": "Maayo gid kag nagakabagay nga dayawon siya.", "2": "kag ginatipon niya ang mga Israelinhon nga nabihag.", "3": "ginabulong niya ang ila mga pilas.", "4": "kag ginhatagan niya ang kada isa sa ila sang ngalan. # 147:4 ginhatagan…ngalan: ukon, ginatawag niya ang kada isa sa ila sa ila nga ngalan # 147:4 ginhatagan…ngalan: ukon, ginatawag niya ang kada isa sa ila sa ila nga ngalan 147:4 ginhatagan…ngalan: ukon, ginatawag niya ang kada isa sa ila sa ila nga ngalan", "5": "ang iya kaalam wala sing limitasyon.", "6": "pero ginalaglag niya sing bug-os ang mga malain.", "7": "Magtukar kamo sang arpa para sa aton Dios.", "8": "kag ginapatubo ang mga hilamon sa mga bukid.", "9": "kag ang mga buto sang uwak kon magpangayo sila sang pagkaon.", "10": "Ang iya kalipay indi sa makusog nga mga kabayo ukon sa madasig nga mga soldado,", "11": "kundi sa mga nagatahod sa iya, nga nagasalig sa iya nga gugma.", "12": "kamo nga mga pumuluyo sang Zion, ang siyudad sang siyudad sang Jerusalem.", "13": "kag ginapakamaayo niya kamo.", "14": "kag ginabusog niya kamo sang pinakamaayo nga trigo.", "15": "kag nagapati ini gilayon.", "16": "kag ginalapta niya ang mapino nga yelo # 147:16 mapino nga yelo: ang buot silingon diri, frost # 147:16 mapino nga yelo: ang buot silingon diri, frost 147:16 mapino nga yelo: ang buot silingon diri, frost nga daw sa abo.", "17": "Wala sing may makaagwanta sang katugnaw sini.", "18": "ginpahangin niya kag nag-ilig ang tubig.", "19": "kag mga sugo sa mga taga-Israel nga mga kaliwat ni Jacob.", "20": "Dayawa ang Ginoo Ginoo !"}