{"1": "And the firmament sheweth his handywork.", "2": "And night unto night sheweth knowledge.", "3": "Where Where their voice is not heard.", "4": "In them hath he set a tabernacle for the sun,", "5": "Which is is as a bridegroom coming out of his chamber, and and rejoiceth as a strong man to run a race.", "6": "And there is nothing hid from the heat thereof.", "7": "The testimony of the LORD LORD is is sure, making wise the simple.", "8": "The commandment of the LORD LORD is is pure, enlightening the eyes.", "9": "The judgments of the LORD LORD are are true and and righteous altogether.", "10": "Sweeter also than honey and the honeycomb.", "11": "And And in keeping of them there is there is great reward.", "12": "Cleanse thou me from secret faults faults .", "13": "Then shall I be upright, and I shall be innocent from the great transgression.", "14": "O LORD LORD , my strength, and my redeemer."}